LICENSE
README.md
setup.py
picpacbayes/__init__.py
picpacbayes/hist_bayes.py
picpacbayes/optim_result_pbayes.py
picpacbayes/pac_bayes_solver.py
picpacbayes/pacbayes_minimize.py
picpacbayes.egg-info/PKG-INFO
picpacbayes.egg-info/SOURCES.txt
picpacbayes.egg-info/dependency_links.txt
picpacbayes.egg-info/requires.txt
picpacbayes.egg-info/top_level.txt
picpacbayes/gradient_based/__init__.py
picpacbayes/gradient_based/fun_evals_dens.py
picpacbayes/gradient_based/gradient_based_solver.py
picpacbayes/gradient_based/optim_result_pbayes_gb.py
picpacbayes/plot/__init__.py
picpacbayes/plot/accu.py
picpacbayes/plot/analysis.py
picpacbayes/plot/hist_bayes.py
picpacbayes/plot/optim_result.py
picpacbayes/plot/score_approx.py
picpacbayes/score_approx/__init__.py
picpacbayes/score_approx/fun_evals_exp.py
picpacbayes/score_approx/gauss_solver.py
picpacbayes/score_approx/pre_exp_solver.py
picpacbayes/score_approx/score_approx_solver.py
picpacbayes/score_approx/sampling/__init__.py
picpacbayes/score_approx/sampling/iid_random.py
picpacbayes/score_approx/sampling/partial_stein.py
picpacbayes/score_approx/weighing/__init__.py
picpacbayes/score_approx/weighing/monte_carlo.py